datademy_helper/__init__.py
datademy_helper/datademy_helper.py
libname/__init__.py
libname/datademy-helper.py
libname/datademy_helper.py
libname/helper.py
datademy_helper-0.0.7.dist-info/METADATA
datademy_helper-0.0.7.dist-info/WHEEL
datademy_helper-0.0.7.dist-info/top_level.txt
datademy_helper-0.0.7.dist-info/RECORD
