Metadata-Version: 2.1
Name: datademy-helper
Version: 0.0.7
Summary: A basic helper package for students of AusBi Datademy
Home-page: UNKNOWN
Author: HaPhan Tran (AusBi Datademy)
Author-email: <haphantran@gmail.com>
License: UNKNOWN
Keywords: python,learner,helper,input,get_int,get_string
Platform: UNKNOWN
Classifier: Development Status :: 1 - Planning
Classifier: Intended Audience :: Developers
Classifier: Programming Language :: Python :: 3
Classifier: Operating System :: Unix
Classifier: Operating System :: MacOS :: MacOS X
Classifier: Operating System :: Microsoft :: Windows
